teleredis/__init__.py
teleredis/teleredis.py
teleredis-0.1.3.dist-info/DESCRIPTION.rst
teleredis-0.1.3.dist-info/METADATA
teleredis-0.1.3.dist-info/RECORD
teleredis-0.1.3.dist-info/WHEEL
teleredis-0.1.3.dist-info/metadata.json
teleredis-0.1.3.dist-info/top_level.txt
