Metadata-Version: 1.2
Name: teleredis
Version: 0.1.3
Summary: Redis backend for Telethon session storage
Home-page: https://github.com/ezdev128/telethon-session-redis
Author: Konstantin M.
Author-email: ezdev128@yandex.com
License: MIT
Download-URL: https://github.com/ezdev128/telethon-session-redis/releases
Keywords: telegram session sessions redis
Platform: UNKNOWN
Classifier: Development Status :: 4 - Beta
Classifier: Intended Audience :: Developers
Classifier: License :: OSI Approved :: MIT License
Classifier: Programming Language :: Python
Classifier: Programming Language :: Python :: 3
Classifier: Programming Language :: Python :: 3.4
Classifier: Programming Language :: Python :: 3.5
Classifier: Programming Language :: Python :: 3.6
Requires-Python: ~=3.4
